tapioca_mailgun/__init__.py
tapioca_mailgun/resource_mapping.py
tapioca_mailgun/tapioca_mailgun.py
tapioca_mailgun-0.1.1.dist-info/DESCRIPTION.rst
tapioca_mailgun-0.1.1.dist-info/METADATA
tapioca_mailgun-0.1.1.dist-info/RECORD
tapioca_mailgun-0.1.1.dist-info/WHEEL
tapioca_mailgun-0.1.1.dist-info/metadata.json
tapioca_mailgun-0.1.1.dist-info/top_level.txt
