Metadata-Version: 2.0
Name: tapioca-mailgun
Version: 0.1.1
Summary: Mailgun API wrapper using tapioca
Home-page: https://github.com/vintasoftware/tapioca-mailgun
Author: Carlos Coelho
Author-email: carlospecter@gmail.com
License: MIT
Keywords: mailgun
Platform: UNKNOWN
Classifier: Development Status :: 5 - Production/Stable
Classifier: Intended Audience :: Developers
Classifier: License :: OSI Approved :: MIT License
Classifier: Natural Language :: English
Classifier: Programming Language :: Python :: 2
Classifier: Programming Language :: Python :: 2.7
Classifier: Programming Language :: Python :: 3
Classifier: Programming Language :: Python :: 3.1
Classifier: Programming Language :: Python :: 3.2
Classifier: Programming Language :: Python :: 3.3
Classifier: Programming Language :: Python :: 3.4
Classifier: Programming Language :: Python :: 3.5
Classifier: Programming Language :: Python :: 3.6
Requires-Dist: tapioca-wrapper (<2)
